setup.py
pyudorandom/__init__.py
pyudorandom/pyudorandom.py
pyudorandom.egg-info/PKG-INFO
pyudorandom.egg-info/SOURCES.txt
pyudorandom.egg-info/dependency_links.txt
pyudorandom.egg-info/top_level.txt