Metadata-Version: 1.1
Name: pyudorandom
Version: 0.0.1
Summary: Generate pseudorandom numbers by using algebra
Home-page: UNKNOWN
Author: Mats Julian Olsen
Author-email: mats@plysjbyen.net
License: UNKNOWN
Platform: UNKNOWN
Classifier: Programming Language :: Python
Classifier: Programming Language :: Python :: 2.7
Classifier: Programming Language :: Python :: 3
